README.md
setup.py
captain/__init__.py
captain/main.py
captain_py.egg-info/PKG-INFO
captain_py.egg-info/SOURCES.txt
captain_py.egg-info/dependency_links.txt
captain_py.egg-info/entry_points.txt
captain_py.egg-info/not-zip-safe
captain_py.egg-info/requires.txt
captain_py.egg-info/top_level.txt