Metadata-Version: 2.1
Name: captain-py
Version: 0.1.0a1
Summary: A modern deploy tool
Home-page: https://github.com/wangwenpei/captain
Author: WANG WENPEI
Author-email: stormxx@1024.engineer
License: MIT
Download-URL: https://github.com/wangwenpei/captain/tarball/master
Keywords: captain,kubernetes,k8s
Platform: UNKNOWN
Provides-Extra: captain
Provides-Extra: dev
Provides-Extra: test
